rexlogger/__init__.py
rexlogger/rexlogger.py
rexlogger-0.1.0.dist-info/LICENSE
rexlogger-0.1.0.dist-info/METADATA
rexlogger-0.1.0.dist-info/WHEEL
rexlogger-0.1.0.dist-info/top_level.txt
rexlogger-0.1.0.dist-info/RECORD
