Metadata-Version: 2.2
Name: rexlogger
Version: 0.1.0
Summary: A stylish console logger with colored output
Home-page: https://github.com/iblamerex/Rexlogger
Author: ReXx™
Author-email: r3x.fr5@gmail.com
Classifier: Programming Language :: Python :: 3
Classifier: License :: OSI Approved :: MIT License
Classifier: Operating System :: OS Independent
Requires-Python: >=3.6
License-File: LICENSE
Requires-Dist: colorama>=0.4.4
Dynamic: author
Dynamic: author-email
Dynamic: classifier
Dynamic: description
Dynamic: description-content-type
Dynamic: home-page
Dynamic: requires-dist
Dynamic: requires-python
Dynamic: summary
